{
  "$schema": "http://json-schema.org/draft-07/schema#",
  "$id": "ebs",
  "description": "Fields required to estimate the carbon footprint and cost of an EBS volume.",
  "type": "object",
  "required": ["volume_type", "size_gb", "region"],
  "properties": {
    "volume_type": {
      "type": "string",
      "title": "Volume Type",
      "description": "EBS volume type.",
      "enum": ["gp2", "gp3", "io1", "io2", "sc1", "st1", "standard"],
      "enumNames": [
        "gp2 — General Purpose SSD (previous generation)",
        "gp3 — General Purpose SSD",
        "io1 — Provisioned IOPS SSD (previous generation)",
        "io2 — Provisioned IOPS SSD",
        "sc1 — Cold HDD",
        "st1 — Throughput Optimized HDD",
        "standard — Magnetic"
      ]
    },
    "size_gb": {
      "type": "number",
      "title": "Size (GB)",
      "description": "Volume size in gigabytes.",
      "minimum": 1,
      "maximum": 65536
    },
    "region": {
      "type": "string",
      "title": "AWS Region",
      "description": "AWS region where the volume will be created.",
      "enum": [
        "us-east-1",
        "us-east-2",
        "us-west-1",
        "us-west-2",
        "us-gov-east-1",
        "us-gov-west-1",
        "ca-central-1",
        "ca-west-1",
        "eu-west-1",
        "eu-west-2",
        "eu-west-3",
        "eu-central-1",
        "eu-central-2",
        "eu-north-1",
        "eu-south-1",
        "eu-south-2",
        "ap-east-1",
        "ap-east-2",
        "ap-southeast-1",
        "ap-southeast-2",
        "ap-southeast-3",
        "ap-southeast-4",
        "ap-southeast-5",
        "ap-southeast-6",
        "ap-southeast-7",
        "ap-northeast-1",
        "ap-northeast-2",
        "ap-northeast-3",
        "ap-south-1",
        "ap-south-2",
        "sa-east-1",
        "il-central-1",
        "me-south-1",
        "me-central-1",
        "mx-central-1",
        "af-south-1"
      ]
    }
  },
  "additionalProperties": false
}
